{
  "kind": "singleType",
  "collectionName": "contact_pages",
  "info": {
    "singularName": "contact-page",
    "pluralName": "contact-pages",
    "displayName": "ContactPage",
    "description": ""
  },
  "options": {
    "draftAndPublish": true
  },
  "pluginOptions": {
    "i18n": {
      "localized": true
    }
  },
  "attributes": {
    "HeroTitle": {
      "type": "string",
      "pluginOptions": {
        "i18n": {
          "localized": true
        }
      }
    },
    "HeroDescription": {
      "type": "text",
      "pluginOptions": {
        "i18n": {
          "localized": true
        }
      }
    },
    "HeroImage": {
      "type": "media",
      "multiple": false,
      "required": false,
      "allowedTypes": [
        "images",
        "files"
      ],
      "pluginOptions": {
        "i18n": {
          "localized": true
        }
      }
    }
  }
}
